django_rahavard/__init__.py
django_rahavard/apps.py
django_rahavard/management/__init__.py
django_rahavard/management/commands/__init__.py
django_rahavard/management/commands/actions.py
django_rahavard/management/commands/check-deploy.py
django_rahavard/management/commands/collectstatic.py
django_rahavard/management/commands/dumpdata.py
django_rahavard/migrations/__init__.py
django_rahavard-0.0.62.dist-info/LICENSE
django_rahavard-0.0.62.dist-info/METADATA
django_rahavard-0.0.62.dist-info/WHEEL
django_rahavard-0.0.62.dist-info/top_level.txt
django_rahavard-0.0.62.dist-info/RECORD
