Metadata-Version: 2.2
Name: django-rahavard
Version: 0.0.62
Summary: A Django App Containing Overridden Django Commands
Home-page: https://github.com/davoudarsalani/django-rahavard
Author: Davoud Arsalani
Author-email: d_arsalani@yahoo.com
License: MIT License
Classifier: Development Status :: 4 - Beta
Classifier: Intended Audience :: Developers
Classifier: Programming Language :: Python :: 3
Classifier: Framework :: Django
Classifier: License :: OSI Approved :: MIT License
Classifier: Topic :: Utilities
Classifier: Topic :: Internet :: WWW/HTTP
Classifier: Topic :: Internet :: WWW/HTTP :: Dynamic Content
Classifier: Operating System :: Unix
Classifier: Operating System :: MacOS :: MacOS X
Classifier: Operating System :: Microsoft :: Windows
Classifier: Environment :: Web Environment
License-File: LICENSE
Requires-Dist: django
Requires-Dist: natsort
Requires-Dist: rahavard
